kuhl_haus/servers/__init__.py
kuhl_haus/servers/mdl_server.py
kuhl_haus/servers/mdp_server.py
kuhl_haus/servers/wds_server.py
kuhl_haus_mdp_servers-0.1.12.dist-info/METADATA
kuhl_haus_mdp_servers-0.1.12.dist-info/WHEEL
kuhl_haus_mdp_servers-0.1.12.dist-info/entry_points.txt
kuhl_haus_mdp_servers-0.1.12.dist-info/licenses/LICENSE.txt
kuhl_haus_mdp_servers-0.1.12.dist-info/RECORD
