Metadata-Version: 2.4
Name: kuhl-haus-mdp-servers
Version: 0.1.12
Summary: Container image build repository for market data processing servers
Author-Email: Tom Pounders <git@oldschool.engineer>
License-File: LICENSE.txt
Classifier: Development Status :: 4 - Beta
Classifier: Programming Language :: Python
Project-URL: Homepage, https://github.com/kuhl-haus/kuhl-haus-mdp-servers
Project-URL: Documentation, https://github.com/kuhl-haus/kuhl-haus-mdp-servers/wiki
Project-URL: Source, https://github.com/kuhl-haus/kuhl-haus-mdp-servers.git
Project-URL: Changelog, https://github.com/kuhl-haus/kuhl-haus-mdp-servers/commits
Project-URL: Tracker, https://github.com/kuhl-haus/kuhl-haus-mdp-servers/issues
Requires-Python: <3.13,>=3.9.21
Requires-Dist: kuhl-haus-mdp
Requires-Dist: websockets
Requires-Dist: aio-pika
Requires-Dist: redis[asyncio]
Requires-Dist: tenacity
Requires-Dist: fastapi
Requires-Dist: uvicorn[standard]
Requires-Dist: pydantic-settings
Requires-Dist: python-dotenv
Requires-Dist: massive
Provides-Extra: testing
Requires-Dist: setuptools; extra == "testing"
Requires-Dist: pdm-backend; extra == "testing"
Requires-Dist: pytest; extra == "testing"
Requires-Dist: pytest-cov; extra == "testing"
